Processador_de_Imagens/__init__.py
Processador_de_Imagens/Processamento/Combinação.py
Processador_de_Imagens/Processamento/Transformação.py
Processador_de_Imagens/Processamento/__init__.py
Processador_de_Imagens/Utilidades/__init__.py
Processador_de_Imagens/Utilidades/io.py
Processador_de_Imagens/Utilidades/plot.py
pacote_de_processamento_de_imagens_com_python_dio-0.0.1.dist-info/METADATA
pacote_de_processamento_de_imagens_com_python_dio-0.0.1.dist-info/WHEEL
pacote_de_processamento_de_imagens_com_python_dio-0.0.1.dist-info/top_level.txt
pacote_de_processamento_de_imagens_com_python_dio-0.0.1.dist-info/RECORD
