Metadata-Version: 2.4
Name: Pacote_de_Processamento_de_Imagens_com_Python_DIO
Version: 0.0.1
Summary: Pacote de Processamento de Imagens com Python DIO
Home-page: https://github.com/FledWriter3840/Pacote-de-Processamento-de-Imagens-com-Python-DIO
Author: Matheus_de_Souza_Soares
Author-email: desouzasoaresmatheus@gmail.com
Requires-Python: >=3.8
Dynamic: author
Dynamic: author-email
Dynamic: description
Dynamic: description-content-type
Dynamic: home-page
Dynamic: requires-python
Dynamic: summary
